routersploit/__init__.py
routersploit/interpreter.py
routersploit/core/__init__.py
routersploit/core/bluetooth/__init__.py
routersploit/core/bluetooth/btle_client.py
routersploit/core/bluetooth/btle/__init__.py
routersploit/core/bluetooth/btle/btle_device.py
routersploit/core/bluetooth/btle/btle_scanner.py
routersploit/core/exploit/__init__.py
routersploit/core/exploit/encoders.py
routersploit/core/exploit/exceptions.py
routersploit/core/exploit/exploit.py
routersploit/core/exploit/option.py
routersploit/core/exploit/payloads.py
routersploit/core/exploit/printer.py
routersploit/core/exploit/shell.py
routersploit/core/exploit/utils.py
routersploit/core/ftp/__init__.py
routersploit/core/ftp/ftp_client.py
routersploit/core/http/__init__.py
routersploit/core/http/http_client.py
routersploit/core/snmp/__init__.py
routersploit/core/snmp/snmp_client.py
routersploit/core/ssh/__init__.py
routersploit/core/ssh/ssh_client.py
routersploit/core/tcp/__init__.py
routersploit/core/tcp/tcp_client.py
routersploit/core/telnet/__init__.py
routersploit/core/telnet/telnet_client.py
routersploit/core/udp/__init__.py
routersploit/core/udp/udp_client.py
routersploit/libs/__init__.py
routersploit/libs/apiros/__init__.py
routersploit/libs/apiros/apiros_client.py
routersploit/libs/lzs/__init__.py
routersploit/libs/lzs/lzs.py
routersploit/modules/__init__.py
routersploit/modules/creds/__init__.py
routersploit/modules/creds/cameras/__init__.py
routersploit/modules/creds/cameras/acti/__init__.py
routersploit/modules/creds/cameras/acti/ftp_default_creds.py
routersploit/modules/creds/cameras/acti/ssh_default_creds.py
routersploit/modules/creds/cameras/acti/telnet_default_creds.py
routersploit/modules/creds/cameras/acti/webinterface_http_form_default_creds.py
routersploit/modules/creds/cameras/american_dynamics/__init__.py
routersploit/modules/creds/cameras/american_dynamics/ftp_default_creds.py
routersploit/modules/creds/cameras/american_dynamics/ssh_default_creds.py
routersploit-3.4.7.dist-info/LICENSE
routersploit-3.4.7.dist-info/METADATA
routersploit-3.4.7.dist-info/WHEEL
routersploit-3.4.7.dist-info/top_level.txt
routersploit-3.4.7.dist-info/RECORD
